rpi/__init__.py
rpi/py.typed
regex_pattern_index-0.1.2.dist-info/METADATA
regex_pattern_index-0.1.2.dist-info/WHEEL
regex_pattern_index-0.1.2.dist-info/RECORD
