Metadata-Version: 2.4
Name: regex-pattern-index
Version: 0.1.2
Summary: WIP index of regex patterns.
Author-email: Hart Traveller <ruling_fiction.0b@icloud.com>
Requires-Python: >=3.11
Provides-Extra: test
Requires-Dist: hypothesis>=6.131.18; extra == 'test'
Requires-Dist: pytest>=8.3.5; extra == 'test'
